<h:div id="top-bar" xmlns:h="http://www.w3.org/1999/xhtml" 
  xmlns:xi="http://www.w3.org/2001/XInclude"
  xmlns:xxi="http://orbeon.org/oxf/xml/xinclude"
  xmlns:xf="http://www.w3.org/2002/xforms" 
  xmlns:xxf="http://orbeon.org/oxf/xml/xforms"
  xmlns:oxf="http://www.orbeon.com/oxf/processors"
  xmlns:fr="http://orbeon.org/oxf/xml/form-runner"
  xmlns:ev="http://www.w3.org/2001/xml-events" 
  xmlns:xl="http://www.w3.org/1999/xlink"
  xmlns:xs="http://www.w3.org/2001/XMLSchema" 
  xmlns:m="http://www.music-encoding.org/ns/mei"
  xmlns:t="http://www.tei-c.org/ns/1.0" 
  xmlns:dcm="http://www.kb.dk/dcm"
  xml:base="http://localhost/editor/forms/mei/">
  
  <h:div id="tab-menu">
    
    <xf:trigger id="work-tab"  appearance="minimal">
      <xf:label>Work</xf:label>
      <xf:action ev:event="DOMActivate">
        <xxf:variable name="uri" 
          select="concat(instance('parameters')/dcm:orbeon_dir,
          '?uri=',
          instance('parameters')/dcm:form_home,
          'edit-work-case.xml&amp;doc=',
          instance('parameters')/dcm:xml_file)"/>
        <xf:action if="instance('temp')/changed='true'">
          <xf:setvalue ref="instance('temp')/target_uri" value="$uri"/>
          <xxf:show dialog="exit-warning-dialog"/>
        </xf:action>	
        <xf:action if="instance('temp')/changed='false'">
          <xf:load resource="{$uri}" show="replace"/>
        </xf:action>
      </xf:action>
    </xf:trigger><xf:trigger id="music-tab" appearance="minimal">
      <xf:label>Music</xf:label>
      <xf:action ev:event="DOMActivate">
        <xxf:variable name="uri" 
          select="concat(instance('parameters')/dcm:orbeon_dir,
          '?uri=',
          instance('parameters')/dcm:form_home,
          'edit-music-case.xml&amp;doc=',
          instance('parameters')/dcm:xml_file)"/>
        <xf:action if="instance('temp')/changed='true'">
          <xf:setvalue ref="instance('temp')/target_uri" value="$uri"/>
          <xxf:show dialog="exit-warning-dialog"/>
        </xf:action>	
        <xf:action if="instance('temp')/changed='false'">
          <xf:load resource="{$uri}" show="replace"/>
        </xf:action>
      </xf:action>
    </xf:trigger><xf:trigger id="source-tab" appearance="minimal">
      <xf:label>Sources</xf:label>
      <xf:action ev:event="DOMActivate">
        <xxf:variable name="uri" 
          select="concat(instance('parameters')/dcm:orbeon_dir,
          '?uri=',
          instance('parameters')/dcm:form_home,
          'edit-source-case.xml&amp;doc=',
          instance('parameters')/dcm:xml_file)"/>
        <xf:action if="instance('temp')/changed='true'">
          <xf:setvalue ref="instance('temp')/target_uri" value="$uri"/>
          <xxf:show dialog="exit-warning-dialog"/>
        </xf:action>	
        <xf:action if="instance('temp')/changed='false'">
          <xf:load resource="{$uri}" show="replace"/>
        </xf:action>
      </xf:action>
    </xf:trigger><xf:trigger id="history-tab" appearance="minimal">
      <xf:label>History</xf:label>
      <xf:action ev:event="DOMActivate">
        <xxf:variable name="uri" 
          select="concat(instance('parameters')/dcm:orbeon_dir,
          '?uri=',
          instance('parameters')/dcm:form_home,
          'edit-history-case.xml&amp;doc=',
          instance('parameters')/dcm:xml_file)"/>
        <xf:action if="instance('temp')/changed='true'">
          <xf:setvalue ref="instance('temp')/target_uri" value="$uri"/>
          <xxf:show dialog="exit-warning-dialog"/>
        </xf:action>	
        <xf:action if="instance('temp')/changed='false'">
          <xf:load resource="{$uri}" show="replace"/>
        </xf:action>
      </xf:action>
    </xf:trigger><xf:trigger  id="bibliography-tab" appearance="minimal">
      <xf:label>Bibliography</xf:label>
      <xf:action ev:event="DOMActivate">
        <xxf:variable name="uri" 
          select="concat(instance('parameters')/dcm:orbeon_dir,
          '?uri=',
          instance('parameters')/dcm:form_home,
          'edit-bibliography-case.xml&amp;doc=',
          instance('parameters')/dcm:xml_file)"/>
        <xf:action if="instance('temp')/changed='true'">
          <xf:setvalue ref="instance('temp')/target_uri" value="$uri"/>
          <xxf:show dialog="exit-warning-dialog"/>
        </xf:action>	
        <xf:action if="instance('temp')/changed='false'">
          <xf:load resource="{$uri}" show="replace"/>
        </xf:action>
      </xf:action>
    </xf:trigger><xf:trigger  id="file-tab"   appearance="minimal">
      <xf:label>File</xf:label>
      <xf:action ev:event="DOMActivate">
        <xxf:variable name="uri" 
          select="concat(instance('parameters')/dcm:orbeon_dir,
          '?uri=',
          instance('parameters')/dcm:form_home,
          'edit-file-case.xml&amp;doc=',
          instance('parameters')/dcm:xml_file)"/>
        <xf:action if="instance('temp')/changed='true'">
          <xf:setvalue ref="instance('temp')/target_uri" value="$uri"/>
          <xxf:show dialog="exit-warning-dialog"/>
        </xf:action>	
        <xf:action if="instance('temp')/changed='false'">
          <xf:load resource="{$uri}" show="replace"/>
        </xf:action>
      </xf:action>
    </xf:trigger>
    
  </h:div>
  
  <h:fieldset id="top_status_bar">
    <xf:group id="editing_status"
      ref="instance('data-instance')/m:meiHead/m:workDesc/m:work/m:titleStmt/m:title[normalize-space(.)][1]">
      <xf:output value="concat(substring(.,1,80), instance('temp')/etc[string-length(instance('data-instance')/m:meiHead/m:workDesc/m:work/m:titleStmt/m:title[1])&gt;80], instance('temp')[changed='true']/change_marker)" id="work_identifier">
        <xf:label/> 
        <xf:action ev:event="xforms-value-changed">
          <xf:load resource="javascript:setPageTitle()"/>
          <!-- copy the first non-empty work title to file title -->
          <xf:setvalue ref="instance('data-instance')/m:meiHead/m:fileDesc/m:titleStmt/m:title[1]" 
            value="instance('data-instance')/m:meiHead/m:workDesc/m:work/m:titleStmt/m:title[normalize-space(.)][1]"/>
        </xf:action>
      </xf:output>
    </xf:group>
  </h:fieldset>
  
  <xxf:dialog id="exit-warning-dialog" appearance="full">
    <!-- The requested URI must be stored in instance('temp')/target_uri prior to opening the dialog -->
    <xf:label>Warning</xf:label>
    <h:p>You have unsaved changes. 
      Do you want to save before proceeding?
    </h:p>
    <h:p>Changes will be lost if you answer "Discard". <h:br/>
      To keep changes, choose "Save".
    </h:p>    
    <xf:trigger appearance="save_proceed_button">
      <xf:label><h:img src="http:/editor/images/save_small.png" alt="Save" title="Save file and proceed"/> Save</xf:label>
      <xf:action ev:event="DOMActivate">
        <xf:dispatch name="language-update" target="form-group"/>
        <xf:send submission="save-to-file"/>
        <xf:load resource="{instance('temp')/target_uri}" show="replace"/>
        <xxf:hide dialog="exit-warning-dialog"/>
      </xf:action>
    </xf:trigger>
    <xf:trigger>
      <xf:label><h:img src="http:/editor/images/discard.png" alt="Discard" title="Discard changes and proceed"/> Discard</xf:label>
      <xf:action ev:event="DOMActivate">
        <xf:load resource="{instance('temp')/target_uri}" show="replace"/>
        <xxf:hide dialog="exit-warning-dialog"/>
      </xf:action>
    </xf:trigger>
  </xxf:dialog>
  
  
  <h:p id="view_menu">
    <!-- test -->
    <!-- to be implemented -->
    <!--<xf:submit submission="save-to-file" appearance="minimal">
      <xf:label>SAVE AS TEMPLATE</xf:label>
      <xf:action ev:event="DOMActivate">
      <xf:setvalue ref="instance('parameters')/dcm:xml_file" value="concat('templates/',.)"/>
      <xf:message value="concat(instance('parameters')/dcm:crud_home,instance('parameters')/dcm:xml_file)"/>
      <xf:dispatch name="language-update" target="form-group"/>
      </xf:action>
      </xf:submit>--> 
    <!-- end test -->    
    
    <xf:trigger appearance="minimal" id="save-button">
      <xf:label><h:img src="http:/editor/images/save.gif" alt="Save" title="Save file"/></xf:label>
      <xf:action ev:event="DOMActivate save">
        <xf:send submission="save-to-file"/>
        <xf:dispatch name="language-update" target="form-group"/>
      </xf:action>
    </xf:trigger><h:a 
      href="http:/storage/present.xq?doc={instance('parameters')/dcm:xml_file}"
      class="xforms-trigger" 
      target="view_{instance('parameters')/dcm:xml_file}"><h:img 
        src="http:/editor/images/html.gif" alt="HTML" title="View as HTML" border="0"/></h:a><h:a 
      href="{instance('parameters')/dcm:server_name}{instance('parameters')/dcm:document_root}{instance('parameters')/dcm:xml_file}"
      class="xforms-trigger" 
      target="xml_{instance('parameters')/dcm:xml_file}"><h:img 
        src="http:/editor/images/xml.gif" alt="XML" title="View XML data" border="0"/></h:a><xf:trigger appearance="minimal">
      <xf:label><h:img 
        src="http:/editor/images/home.gif" alt="File list" 
        title="Close editor and return to file list" border="0"/></xf:label>
      <xf:action ev:event="DOMActivate">
        <xf:action if="instance('temp')/changed='true'">
          <xxf:variable name="uri" select="concat(instance('parameters')/dcm:server_name,instance('parameters')/dcm:exist_dir,'list_files.xq')"/>
          <xf:setvalue ref="instance('temp')/target_uri" value="$uri"/>
          <xxf:show dialog="exit-warning-dialog"/>
        </xf:action>	
        <xf:action if="instance('temp')/changed='false'">
          <xf:load resource="{instance('parameters')/dcm:server_name}{instance('parameters')/dcm:exist_dir}list_files.xq" show="replace"/>
        </xf:action>
      </xf:action>
    </xf:trigger><xf:trigger appearance="minimal">
      <xf:label><h:img 
        src="http:/editor/images/settings.png" alt="Settings" 
        title="Change settings" border="0"/></xf:label>
      <xf:action ev:event="DOMActivate">
        <xxf:show dialog="settings-dialog"/>
      </xf:action>
    </xf:trigger><xf:trigger appearance="minimal">
      <xf:label><h:img 
        src="http:/editor/images/help.png" alt="Help" 
        title="Help" border="0"/></xf:label>
      <xf:action ev:event="DOMActivate">
        <xf:load resource="{instance('parameters')/dcm:server_name}/editor/manual/index.html" show="new"/>
      </xf:action>
    </xf:trigger>
  </h:p>
  
  <!-- Dialog for editing session settings and opening standard (template) data editors -->
  <xxf:dialog id="settings-dialog" appearance="full" level="modal">
    <xf:label>MerMEId settings</xf:label>
    <xf:trigger appearance="minimal">
      <xf:label><h:img src="http:/editor/images/expand.png" title="Edit"/> Edit standard bibliographic references <h:a class="help">?<h:span class="comment">For each 
      file collection (series), a list of frequently used bibliographic references may be available when adding
      a new reference at the "Bibliography" tab. The lists may be edited using this menu option.</h:span></h:a>
      </xf:label>
      <xf:action ev:event="DOMActivate">
        <xf:insert context="." origin="xxf:set-session-attribute('return_url',instance('parameters')/dcm:this_page)"/>
        <xf:load resource="{instance('parameters')/dcm:orbeon_dir}/?uri={instance('parameters')/dcm:form_home}model-references.xml"></xf:load>
      </xf:action>
    </xf:trigger>
    <h:br/>&#160;
    <!-- to be implemented     
      <xf:trigger appearance="minimal">
      <xf:label><h:img src="http:/editor/images/expand.png" title="Edit"/> Edit standard instrumentations <h:a class="help">?<h:span 
      class="comment">Edit the standard ensembles and instrument groups available when adding new instruments 
      at the "Music" tab.</h:span></h:a></xf:label>
      <xf:action ev:event="DOMActivate">
      <xf:insert context="." origin="xxf:set-session-attribute('return_url',instance('parameters')/dcm:this_page)"/>
      <xf:load resource="{instance('parameters')/dcm:orbeon_dir}/?uri={instance('parameters')/dcm:form_home}model-instrumentations.xml"></xf:load>
      </xf:action>
      </xf:trigger>-->
    
    <h:hr/>
    <xf:group ref=".[contains(instance('parameters')/dcm:id_main_switch,'true')]">
      <xf:select appearance="full" ref="instance('parameters')/dcm:show_id">
        <xf:action ev:event="xforms-value-changed">
          <xf:insert context="." origin="xxf:set-session-attribute('show_id',instance('parameters')/dcm:show_id)"/>
        </xf:action>
        <xf:item>
          <xf:label>Show xml:id values <h:a class="help">?<h:span class="comment">Displays an ID icon 
            (<h:img src="http:/editor/images/id.png" border="0" alt="ID Icon"/>) next to selected elements.
            The element's xml:id attribute value is displayed when moving the cursor over the icon.
          </h:span></h:a></xf:label>
          <xf:value>true</xf:value>
        </xf:item>      
      </xf:select>
    </xf:group>
    <h:div class="vertical_spacer"/>
    <!--
      <h:p><b>Advanced settings</b></h:p>-->
    <xf:group ref=".[contains(instance('parameters')/dcm:attr_editor_main_switch,'true')]">
      <xf:select appearance="full" ref="instance('parameters')/dcm:attr_editor">
        <xf:action ev:event="xforms-value-changed">
          <xf:insert context="." origin="xxf:set-session-attribute('attr_editor',instance('parameters')/dcm:attr_editor)"/>
        </xf:action>
        <xf:item>
          <xf:label>Enable attribute editor <h:a class="help_plain"><h:img 
            src="http:/editor/images/warning.png" alt="warning"/><h:span class="comment">This enables changing or adding
              all possible attributes according to the XML schema. Changing attributes may compromise the validity 
              of your data and affect the way MerMEId displays them. 
              Use the attribute editor only if you know what you are doing.
            </h:span></h:a></xf:label>
          <xf:value>true</xf:value>
        </xf:item>      
      </xf:select>
    </xf:group>
    <!-- code inspector -->
    <xf:group ref=".[contains(instance('parameters')/dcm:code_inspector_main_switch,'true')]">
      <h:div class="vertical_spacer"/>
      <xf:select appearance="full" ref="instance('parameters')/dcm:code_inspector">
        <xf:action ev:event="xforms-value-changed">
          <xf:insert context="." origin="xxf:set-session-attribute('code_inspector',instance('parameters')/dcm:code_inspector)"/>
        </xf:action>
        <xf:item>
          <xf:label>Enable code inspector <h:a class="help">?<h:span class="comment">The
            code inspector allows you to inspect your XML data as you edit.<h:br/>
            The code inspector will be displayed at the bottom of the page.<h:br/>
            Please note: The code inspector has occasionally proved to require extreme server resources,
            sometimes even causing the server to crash. Use it carefully (and of course completely at own risk).
          </h:span></h:a></xf:label>
          <xf:value>true</xf:value>
        </xf:item>      
      </xf:select>
    </xf:group>
    <!-- end code inspector -->
  </xxf:dialog>
  
  
</h:div>

